{
    "key": "group_58e2c0ee2e9c1",
    "title": "Footer",
    "fields": [
        {
            "key": "field_58e2c0feccbd1",
            "label": "Footer Link ES",
            "name": "footer_link_es",
            "type": "email",
            "instructions": "",
            "required": 0,
            "conditional_logic": 0,
            "wrapper": {
                "width": "",
                "class": "",
                "id": ""
            },
            "default_value": "",
            "placeholder": "",
            "prepend": "",
            "append": ""
        },
        {
            "key": "field_58e2c145ccbd3",
            "label": "Footer Link EN",
            "name": "footer_link_en",
            "type": "email",
            "instructions": "",
            "required": 0,
            "conditional_logic": 0,
            "wrapper": {
                "width": "",
                "class": "",
                "id": ""
            },
            "default_value": "",
            "placeholder": "",
            "prepend": "",
            "append": ""
        },
        {
            "key": "field_58e2c137ccbd2",
            "label": "Footer Direction ES",
            "name": "footer_direction_es",
            "type": "text",
            "instructions": "",
            "required": 0,
            "conditional_logic": 0,
            "wrapper": {
                "width": "",
                "class": "",
                "id": ""
            },
            "default_value": "",
            "placeholder": "",
            "prepend": "",
            "append": "",
            "maxlength": ""
        },
        {
            "key": "field_58e2c14eccbd4",
            "label": "Footer Direction EN",
            "name": "footer_direction_en",
            "type": "text",
            "instructions": "",
            "required": 0,
            "conditional_logic": 0,
            "wrapper": {
                "width": "",
                "class": "",
                "id": ""
            },
            "default_value": "",
            "maxlength": "",
            "placeholder": "",
            "prepend": "",
            "append": ""
        },
        {
            "key": "field_58e2ca8937190",
            "label": "Instagram",
            "name": "instagram",
            "type": "url",
            "instructions": "",
            "required": 0,
            "conditional_logic": 0,
            "wrapper": {
                "width": "",
                "class": "",
                "id": ""
            },
            "default_value": "",
            "placeholder": ""
        },
        {
            "key": "field_58e2ca9337191",
            "label": "Facebook",
            "name": "facebook",
            "type": "url",
            "instructions": "",
            "required": 0,
            "conditional_logic": 0,
            "wrapper": {
                "width": "",
                "class": "",
                "id": ""
            },
            "default_value": "",
            "placeholder": ""
        },
        {
            "key": "field_58e2ca9d37192",
            "label": "Twitter",
            "name": "twitter",
            "type": "url",
            "instructions": "",
            "required": 0,
            "conditional_logic": 0,
            "wrapper": {
                "width": "",
                "class": "",
                "id": ""
            },
            "default_value": "",
            "placeholder": ""
        }
    ],
    "location": [
        [
            {
                "param": "options_page",
                "operator": "==",
                "value": "acf-options-footer"
            }
        ]
    ],
    "menu_order": 0,
    "position": "normal",
    "style": "default",
    "label_placement": "top",
    "instruction_placement": "label",
    "hide_on_screen": "",
    "active": 1,
    "description": "",
    "modified": 1491758943
}